MANIFEST.in
README.rst
requirements.txt
setup.cfg
setup.py
django_microsip_base/Servidor SIC.exe
django_microsip_base/Servidor_celeryd.cmd
django_microsip_base/__init__.py
django_microsip_base/__init__.pyc
django_microsip_base/logo.ico
django_microsip_base/logo_serv.ico
django_microsip_base/manage_dev_plus.py
django_microsip_base/manage_dev_plus.pyc
django_microsip_base/manage_prod.py
django_microsip_base/manage_prod.pyc
django_microsip_base/manage_test.py
django_microsip_base/manage_test.pyc
django_microsip_base/paramiko.log
django_microsip_base.egg-info/PKG-INFO
django_microsip_base.egg-info/SOURCES.txt
django_microsip_base.egg-info/dependency_links.txt
django_microsip_base.egg-info/requires.txt
django_microsip_base.egg-info/top_level.txt
django_microsip_base/django_microsip_base/__init__.py
django_microsip_base/django_microsip_base/__init__.pyc
django_microsip_base/django_microsip_base/context_processors.pyc
django_microsip_base/django_microsip_base/wsgi.pyc
django_microsip_base/django_microsip_base/apps/__init__.py
django_microsip_base/django_microsip_base/apps/__init__.pyc
django_microsip_base/django_microsip_base/apps/main/__init__.py
django_microsip_base/django_microsip_base/apps/main/__init__.pyc
django_microsip_base/django_microsip_base/apps/main/autocomplete_light_registry.pyc
django_microsip_base/django_microsip_base/apps/main/urls.pyc
django_microsip_base/django_microsip_base/apps/main/views.pyc
django_microsip_base/django_microsip_base/data/info.txt
django_microsip_base/django_microsip_base/libs/__init__.py
django_microsip_base/django_microsip_base/libs/__init__.pyc
django_microsip_base/django_microsip_base/libs/databases_routers.py
django_microsip_base/django_microsip_base/libs/databases_routers.pyc
django_microsip_base/django_microsip_base/libs/databases_routers_tests.py
django_microsip_base/django_microsip_base/libs/databases_routers_tests.pyc
django_microsip_base/django_microsip_base/libs/models_base/__init__.py
django_microsip_base/django_microsip_base/libs/models_base/__init__.pyc
django_microsip_base/django_microsip_base/libs/models_base/models.pyc
django_microsip_base/django_microsip_base/media/__init__.txt
