Metadata-Version: 1.1
Name: django-microsip-base
Version: 2.1.9
Summary: Django Microsip Base
Home-page: UNKNOWN
Author: Servicios de Ingenieria Computacional
Author-email: desarrollo@siccomputacion.com
License: UNKNOWN
Platform: UNKNOWN
Classifier: Environment :: Web Environment
Classifier: Framework :: Django
Classifier: Intended Audience :: Developers
Classifier: License :: OSI Approved :: BSD License
Classifier: Operating System :: OS Independent
Classifier: Programming Language :: Python
Classifier: Programming Language :: Python :: 2.6
Classifier: Programming Language :: Python :: 2.7
Classifier: Topic :: Internet :: WWW/HTTP
Classifier: Topic :: Internet :: WWW/HTTP :: Dynamic Content
